skintone/__init__.py
skintone/shell/__init__.py
skintone/shell/usage.py
skintone/src/__init__.py
skintone/src/kintone.py
skintone/src/kintone_file.py
skintone-0.0.1.dist-info/licenses/LICENSE
skintone-0.0.1.dist-info/METADATA
skintone-0.0.1.dist-info/WHEEL
skintone-0.0.1.dist-info/entry_points.txt
skintone-0.0.1.dist-info/top_level.txt
skintone-0.0.1.dist-info/zip-safe
skintone-0.0.1.dist-info/RECORD
